Metadata-Version: 2.1
Name: rust-dll-example
Version: 0.1.1
License: MIT
